Metadata-Version: 2.1
Name: para-attn
Version: 0.3.30
Summary: Context parallel attention that works with torch.compile
Author-email: Zeyi Cheng <ichengzeyi@gmail.com>
Project-URL: Repository, https://github.com/chengzeyi/ParaAttention
Requires-Python: >=3.8
Provides-Extra: all
Provides-Extra: dev
License-File: LICENSE.md
